{
  "date": "2026-03-03",
  "limit_up": [
    {
      "name": "亚盛集团",
      "code": "600108",
      "continuous_days": 3,
      "reason": "两会;农业",
      "price": 4.81,
      "change_pct": 10.07,
      "amount": 22.45,
      "turnover_rate": 24.04
    },
    {
      "name": "和顺石油",
      "code": "603353",
      "continuous_days": 3,
      "reason": "油服",
      "price": 50.97,
      "change_pct": 9.99,
      "amount": 9.81,
      "turnover_rate": 11.45
    },
    {
      "name": "华盛昌",
      "code": "002980",
      "continuous_days": 3,
      "reason": "AI;油服",
      "price": 35.06,
      "change_pct": 10.01,
      "amount": 14.94,
      "turnover_rate": 60.24
    },
    {
      "name": "水发燃气",
      "code": "603318",
      "continuous_days": 3,
      "reason": "天然气;油服",
      "price": 9.7,
      "change_pct": 9.98,
      "amount": 1.34,
      "turnover_rate": 3.59
    },
    {
      "name": "通源石油",
      "code": "300164",
      "continuous_days": 2,
      "reason": "油服",
      "price": 21.7,
      "change_pct": 20.02,
      "amount": 30.81,
      "turnover_rate": 24.77
    },
    {
      "name": "潜能恒信",
      "code": "300191",
      "continuous_days": 2,
      "reason": "油服",
      "price": 53.08,
      "change_pct": 20.01,
      "amount": 22.07,
      "turnover_rate": 19.43
    },
    {
      "name": "德石股份",
      "code": "301158",
      "continuous_days": 2,
      "reason": "油服",
      "price": 37.44,
      "change_pct": 20.0,
      "amount": 13.67,
      "turnover_rate": 26.38
    },
    {
      "name": "华如科技",
      "code": "301302",
      "continuous_days": 2,
      "reason": "军工",
      "price": 35.66,
      "change_pct": 19.99,
      "amount": 9.42,
      "turnover_rate": 31.41
    },
    {
      "name": "广聚能源",
      "code": "000096",
      "continuous_days": 2,
      "reason": "油服",
      "price": 13.27,
      "change_pct": 10.03,
      "amount": 12.66,
      "turnover_rate": 19.19
    },
    {
      "name": "泰山石油",
      "code": "000554",
      "continuous_days": 2,
      "reason": "油服",
      "price": 10.85,
      "change_pct": 10.04,
      "amount": 2.39,
      "turnover_rate": 6.09
    },
    {
      "name": "蓝焰控股",
      "code": "000968",
      "continuous_days": 2,
      "reason": "油服",
      "price": 10.41,
      "change_pct": 10.04,
      "amount": 9.24,
      "turnover_rate": 9.21
    },
    {
      "name": "南 京 港",
      "code": "002040",
      "continuous_days": 2,
      "reason": "航运;油服",
      "price": 13.17,
      "change_pct": 10.03,
      "amount": 13.42,
      "turnover_rate": 21.49
    },
    {
      "name": "准油股份",
      "code": "002207",
      "continuous_days": 2,
      "reason": "油服",
      "price": 13.66,
      "change_pct": 9.98,
      "amount": 0.48,
      "turnover_rate": 1.34
    },
    {
      "name": "山东墨龙",
      "code": "002490",
      "continuous_days": 2,
      "reason": "油服",
      "price": 10.65,
      "change_pct": 10.02,
      "amount": 0.42,
      "turnover_rate": 0.73
    },
    {
      "name": "惠博普",
      "code": "002554",
      "continuous_days": 2,
      "reason": "油服",
      "price": 5.13,
      "change_pct": 10.09,
      "amount": 14.53,
      "turnover_rate": 21.62
    },
    {
      "name": "仁智股份",
      "code": "002629",
      "continuous_days": 2,
      "reason": "油服",
      "price": 8.11,
      "change_pct": 10.04,
      "amount": 10.17,
      "turnover_rate": 35.91
    },
    {
      "name": "贝肯能源",
      "code": "002828",
      "continuous_days": 2,
      "reason": "油服",
      "price": 16.37,
      "change_pct": 10.01,
      "amount": 3.99,
      "turnover_rate": 12.69
    },
    {
      "name": "中远海能",
      "code": "600026",
      "continuous_days": 2,
      "reason": "航运;油服",
      "price": 24.9,
      "change_pct": 9.98,
      "amount": 32.47,
      "turnover_rate": 3.82
    },
    {
      "name": "中国石化",
      "code": "600028",
      "continuous_days": 2,
      "reason": "油服",
      "price": 7.82,
      "change_pct": 9.99,
      "amount": 114.16,
      "turnover_rate": 1.58
    },
    {
      "name": "广汇能源",
      "code": "600256",
      "continuous_days": 2,
      "reason": "油服",
      "price": 7.12,
      "change_pct": 10.05,
      "amount": 68.37,
      "turnover_rate": 15.08
    },
    {
      "name": "中油工程",
      "code": "600339",
      "continuous_days": 2,
      "reason": "油服",
      "price": 5.13,
      "change_pct": 10.09,
      "amount": 6.03,
      "turnover_rate": 2.13
    },
    {
      "name": "红星发展",
      "code": "600367",
      "continuous_days": 2,
      "reason": "锂电池",
      "price": 25.91,
      "change_pct": 10.02,
      "amount": 26.49,
      "turnover_rate": 32.38
    },
    {
      "name": "海油工程",
      "code": "600583",
      "continuous_days": 2,
      "reason": "油服",
      "price": 8.72,
      "change_pct": 9.96,
      "amount": 33.43,
      "turnover_rate": 8.79
    },
    {
      "name": "上海石化",
      "code": "600688",
      "continuous_days": 2,
      "reason": "油服",
      "price": 3.84,
      "change_pct": 10.03,
      "amount": 20.81,
      "turnover_rate": 7.51
    },
    {
      "name": "金瑞矿业",
      "code": "600714",
      "continuous_days": 2,
      "reason": "有色金属",
      "price": 21.74,
      "change_pct": 10.02,
      "amount": 5.73,
      "turnover_rate": 9.15
    },
    {
      "name": "金牛化工",
      "code": "600722",
      "continuous_days": 2,
      "reason": "化工;甲醇",
      "price": 11.35,
      "change_pct": 9.98,
      "amount": 1.12,
      "turnover_rate": 1.45
    },
    {
      "name": "中海油服",
      "code": "601808",
      "continuous_days": 2,
      "reason": "油服",
      "price": 20.42,
      "change_pct": 10.02,
      "amount": 22.99,
      "turnover_rate": 3.91
    },
    {
      "name": "中国石油",
      "code": "601857",
      "continuous_days": 2,
      "reason": "油服",
      "price": 13.15,
      "change_pct": 10.04,
      "amount": 117.48,
      "turnover_rate": 0.57
    },
    {
      "name": "招商轮船",
      "code": "601872",
      "continuous_days": 2,
      "reason": "航运;油服",
      "price": 19.65,
      "change_pct": 10.02,
      "amount": 72.62,
      "turnover_rate": 4.69
    },
    {
      "name": "中曼石油",
      "code": "603619",
      "continuous_days": 2,
      "reason": "油服",
      "price": 43.99,
      "change_pct": 10.0,
      "amount": 6.7,
      "turnover_rate": 3.3
    },
    {
      "name": "博迈科",
      "code": "603727",
      "continuous_days": 2,
      "reason": "油服",
      "price": 21.79,
      "change_pct": 9.99,
      "amount": 9.23,
      "turnover_rate": 15.27
    },
    {
      "name": "招商南油",
      "code": "601975",
      "continuous_days": 2,
      "reason": "航运;油服",
      "price": 4.97,
      "change_pct": 9.96,
      "amount": 16.93,
      "turnover_rate": 7.11
    },
    {
      "name": "海油发展",
      "code": "600968",
      "continuous_days": 2,
      "reason": "油服",
      "price": 5.54,
      "change_pct": 9.92,
      "amount": 14.26,
      "turnover_rate": 2.56
    },
    {
      "name": "中国海油",
      "code": "600938",
      "continuous_days": 2,
      "reason": "油服",
      "price": 43.41,
      "change_pct": 10.01,
      "amount": 108.26,
      "turnover_rate": 8.46
    },
    {
      "name": "洲际油气",
      "code": "600759",
      "continuous_days": 2,
      "reason": "油服",
      "price": 7.51,
      "change_pct": 9.96,
      "amount": 2.25,
      "turnover_rate": 0.72
    },
    {
      "name": "石化油服",
      "code": "600871",
      "continuous_days": 2,
      "reason": "油服",
      "price": 3.88,
      "change_pct": 9.92,
      "amount": 1.75,
      "turnover_rate": 0.33
    },
    {
      "name": "新天然气",
      "code": "603393",
      "continuous_days": 2,
      "reason": "天然气;油服",
      "price": 41.23,
      "change_pct": 10.01,
      "amount": 26.2,
      "turnover_rate": 15.24
    },
    {
      "name": "泰嘉股份",
      "code": "002843",
      "continuous_days": 0,
      "reason": "算力;AI",
      "price": 28.99,
      "change_pct": 4.28,
      "amount": 28.89,
      "turnover_rate": 39.8
    },
    {
      "name": "赤天化",
      "code": "600227",
      "continuous_days": 0,
      "reason": "甲醇;化工",
      "price": 3.34,
      "change_pct": 5.36,
      "amount": 12.53,
      "turnover_rate": 28.78
    },
    {
      "name": "长源东谷",
      "code": "603950",
      "continuous_days": 0,
      "reason": "燃气轮机;AI",
      "price": 50.0,
      "change_pct": 2.12,
      "amount": 14.56,
      "turnover_rate": 8.75
    },
    {
      "name": "德业股份",
      "code": "605117",
      "continuous_days": 0,
      "reason": "光伏",
      "price": 121.96,
      "change_pct": 6.1,
      "amount": 32.89,
      "turnover_rate": 4.09
    },
    {
      "name": "汇绿生态",
      "code": "001267",
      "continuous_days": 0,
      "reason": "光通信;AI",
      "price": 35.0,
      "change_pct": 4.32,
      "amount": 38.41,
      "turnover_rate": 18.63
    },
    {
      "name": "北京科锐",
      "code": "002350",
      "continuous_days": 1,
      "reason": "电力",
      "price": 13.08,
      "change_pct": 10.01,
      "amount": 10.22,
      "turnover_rate": 15.6
    },
    {
      "name": "龙洲股份",
      "code": "002682",
      "continuous_days": 1,
      "reason": "福建自贸/海西概念",
      "price": 7.67,
      "change_pct": 10.04,
      "amount": 8.61,
      "turnover_rate": 20.44
    },
    {
      "name": "大有能源",
      "code": "600403",
      "continuous_days": 1,
      "reason": "煤炭",
      "price": 7.88,
      "change_pct": 10.06,
      "amount": 12.17,
      "turnover_rate": 6.67
    },
    {
      "name": "韩建河山",
      "code": "603616",
      "continuous_days": 1,
      "reason": "管网",
      "price": 8.17,
      "change_pct": 9.96,
      "amount": 1.95,
      "turnover_rate": 6.41
    },
    {
      "name": "亚世光电",
      "code": "002952",
      "continuous_days": 1,
      "reason": "消费电子",
      "price": 24.43,
      "change_pct": 10.0,
      "amount": 2.08,
      "turnover_rate": 6.59
    },
    {
      "name": "康惠股份",
      "code": "603139",
      "continuous_days": 1,
      "reason": "医药",
      "price": 28.13,
      "change_pct": 10.01,
      "amount": 1.83,
      "turnover_rate": 6.75
    }
  ],
  "limit_broken": [
    {
      "name": "艾罗能源",
      "code": "688717",
      "continuous_days": 0,
      "reason": "光伏",
      "price": 125.14,
      "change_pct": 12.74,
      "amount": 20.58,
      "turnover_rate": 16.57
    },
    {
      "name": "首航新能",
      "code": "301658",
      "continuous_days": 0,
      "reason": "光伏",
      "price": 36.09,
      "change_pct": 13.49,
      "amount": 7.48,
      "turnover_rate": 52.38
    },
    {
      "name": "凤凰航运",
      "code": "000520",
      "continuous_days": 0,
      "reason": "航运",
      "price": 5.11,
      "change_pct": 8.03,
      "amount": 7.65,
      "turnover_rate": 15.08
    },
    {
      "name": "豫能控股",
      "code": "001896",
      "continuous_days": 0,
      "reason": "云计算数据中心",
      "price": 13.28,
      "change_pct": -6.08,
      "amount": 37.94,
      "turnover_rate": 17.05
    },
    {
      "name": "联创电子",
      "code": "002036",
      "continuous_days": 0,
      "reason": "无人驾驶",
      "price": 11.22,
      "change_pct": 4.18,
      "amount": 16.74,
      "turnover_rate": 13.8
    },
    {
      "name": "中利集团",
      "code": "002309",
      "continuous_days": 0,
      "reason": "光伏",
      "price": 3.38,
      "change_pct": 0.0,
      "amount": 8.85,
      "turnover_rate": 20.99
    },
    {
      "name": "通鼎互联",
      "code": "002491",
      "continuous_days": 0,
      "reason": "光通信;AI",
      "price": 12.12,
      "change_pct": 8.99,
      "amount": 37.36,
      "turnover_rate": 26.36
    },
    {
      "name": "跃岭股份",
      "code": "002725",
      "continuous_days": 0,
      "reason": "磷化工",
      "price": 16.45,
      "change_pct": 3.52,
      "amount": 8.32,
      "turnover_rate": 23.17
    },
    {
      "name": "丰元股份",
      "code": "002805",
      "continuous_days": 0,
      "reason": "锂电池",
      "price": 16.66,
      "change_pct": 2.52,
      "amount": 5.85,
      "turnover_rate": 12.33
    },
    {
      "name": "泰嘉股份",
      "code": "002843",
      "continuous_days": 0,
      "reason": "算力;AI",
      "price": 28.99,
      "change_pct": 4.28,
      "amount": 28.89,
      "turnover_rate": 39.8
    },
    {
      "name": "润建股份",
      "code": "002929",
      "continuous_days": 0,
      "reason": "云计算数据中心",
      "price": 49.48,
      "change_pct": 3.41,
      "amount": 22.51,
      "turnover_rate": 20.94
    },
    {
      "name": "廊坊发展",
      "code": "600149",
      "continuous_days": 0,
      "reason": "北京城市规划",
      "price": 6.34,
      "change_pct": 4.62,
      "amount": 4.68,
      "turnover_rate": 19.01
    },
    {
      "name": "兖矿能源",
      "code": "600188",
      "continuous_days": 0,
      "reason": "",
      "price": 20.5,
      "change_pct": 8.75,
      "amount": 37.61,
      "turnover_rate": 3.23
    },
    {
      "name": "赤天化",
      "code": "600227",
      "continuous_days": 0,
      "reason": "甲醇;化工",
      "price": 3.34,
      "change_pct": 5.36,
      "amount": 12.53,
      "turnover_rate": 28.78
    },
    {
      "name": "京投发展",
      "code": "600683",
      "continuous_days": 0,
      "reason": "其他",
      "price": 6.99,
      "change_pct": 1.9,
      "amount": 3.71,
      "turnover_rate": 6.91
    },
    {
      "name": "潞化科技",
      "code": "600691",
      "continuous_days": 0,
      "reason": "烧碱",
      "price": 3.63,
      "change_pct": 6.45,
      "amount": 8.59,
      "turnover_rate": 9.97
    },
    {
      "name": "山西焦化",
      "code": "600740",
      "continuous_days": 0,
      "reason": "煤炭",
      "price": 5.17,
      "change_pct": 4.23,
      "amount": 13.52,
      "turnover_rate": 10.22
    },
    {
      "name": "三祥新材",
      "code": "603663",
      "continuous_days": 0,
      "reason": "固态电池",
      "price": 52.64,
      "change_pct": 6.06,
      "amount": 13.57,
      "turnover_rate": 5.99
    },
    {
      "name": "长源东谷",
      "code": "603950",
      "continuous_days": 0,
      "reason": "燃气轮机;AI",
      "price": 50.0,
      "change_pct": 2.12,
      "amount": 14.56,
      "turnover_rate": 8.75
    },
    {
      "name": "新天绿能",
      "code": "600956",
      "continuous_days": 0,
      "reason": "",
      "price": 8.71,
      "change_pct": 9.84,
      "amount": 5.07,
      "turnover_rate": 2.56
    },
    {
      "name": "金富科技",
      "code": "003018",
      "continuous_days": 0,
      "reason": "资产重组",
      "price": 27.27,
      "change_pct": 4.48,
      "amount": 6.89,
      "turnover_rate": 18.74
    },
    {
      "name": "德业股份",
      "code": "605117",
      "continuous_days": 0,
      "reason": "光伏",
      "price": 121.96,
      "change_pct": 6.1,
      "amount": 32.89,
      "turnover_rate": 4.09
    },
    {
      "name": "汇绿生态",
      "code": "001267",
      "continuous_days": 0,
      "reason": "光通信;AI",
      "price": 35.0,
      "change_pct": 4.32,
      "amount": 38.41,
      "turnover_rate": 18.63
    },
    {
      "name": "锦江航运",
      "code": "601083",
      "continuous_days": 0,
      "reason": "航运",
      "price": 13.72,
      "change_pct": 9.94,
      "amount": 7.91,
      "turnover_rate": 30.69
    },
    {
      "name": "华银电力",
      "code": "600744",
      "continuous_days": 0,
      "reason": "",
      "price": 8.39,
      "change_pct": 5.14,
      "amount": 33.38,
      "turnover_rate": 19.85
    },
    {
      "name": "翠微股份",
      "code": "603123",
      "continuous_days": 0,
      "reason": "数字人民币",
      "price": 13.69,
      "change_pct": 4.66,
      "amount": 13.24,
      "turnover_rate": 14.51
    },
    {
      "name": "中煤能源",
      "code": "601898",
      "continuous_days": 0,
      "reason": "煤炭",
      "price": 17.49,
      "change_pct": 5.68,
      "amount": 25.43,
      "turnover_rate": 1.62
    },
    {
      "name": "中远海控",
      "code": "601919",
      "continuous_days": 0,
      "reason": "",
      "price": 16.96,
      "change_pct": 9.84,
      "amount": 91.49,
      "turnover_rate": 4.45
    },
    {
      "name": "云煤能源",
      "code": "600792",
      "continuous_days": 0,
      "reason": "煤炭",
      "price": 5.42,
      "change_pct": 9.72,
      "amount": 6.69,
      "turnover_rate": 12.19
    },
    {
      "name": "渤海化学",
      "code": "600800",
      "continuous_days": 0,
      "reason": "",
      "price": 4.82,
      "change_pct": 6.87,
      "amount": 5.72,
      "turnover_rate": 11.06
    }
  ],
  "summary": {
    "zt_all": 77,
    "seal_rate": 71.96
  },
  "history_10d": [
    {
      "date": "2026-02-10",
      "up_count": 2367.0,
      "down_count": 3106.0,
      "zt_all": 60.0,
      "dt_count": 7.0,
      "lb_count": 21.0,
      "up10_count": 71.0,
      "down9_count": 17.0,
      "yizi_count": 10.0,
      "shouban": 39.0,
      "er_lb": 20.0,
      "san_lb": 1.0,
      "si_lb": 0.0,
      "wu_lb": 0.0,
      "zt_925": 13.0,
      "t_before10": 33.0,
      "t_1000_1130": 20.0,
      "t_1300_1400": 3.0,
      "t_1400_1500": 3.0,
      "limit_broken_count": 14.0,
      "seal_rate": 81.08,
      "rate_1to2": 28.17,
      "rate_2to3": 9.09,
      "rate_3to4": 0.0,
      "lb_rate": 35.0,
      "lb_rate_prev": 24.42,
      "zt_amount": 1111.75,
      "total_amount": 2741.75,
      "sh_amount": 8822.02,
      "cyb_amount": 5925.68,
      "kcb_amount": 2191.2
    },
    {
      "date": "2026-02-11",
      "up_count": 2223.0,
      "down_count": 3277.0,
      "zt_all": 51.0,
      "dt_count": 10.0,
      "lb_count": 11.0,
      "up10_count": 60.0,
      "down9_count": 27.0,
      "yizi_count": 5.0,
      "shouban": 75.0,
      "er_lb": 91.0,
      "san_lb": 33.0,
      "si_lb": 0.0,
      "wu_lb": 0.0,
      "zt_925": 9.0,
      "t_before10": 85.0,
      "t_1000_1130": 80.0,
      "t_1300_1400": 60.0,
      "t_1400_1500": 75.0,
      "limit_broken_count": 18.0,
      "seal_rate": 73.91,
      "rate_1to2": 7.69,
      "rate_2to3": 35.0,
      "rate_3to4": 100.0,
      "lb_rate": 21.57,
      "lb_rate_prev": 18.33,
      "zt_amount": 832.91,
      "total_amount": 2377.91,
      "sh_amount": 8226.08,
      "cyb_amount": 5602.98,
      "kcb_amount": 1799.23
    },
    {
      "date": "2026-02-12",
      "up_count": 2151.0,
      "down_count": 3265.0,
      "zt_all": 60.0,
      "dt_count": 17.0,
      "lb_count": 17.0,
      "up10_count": 84.0,
      "down9_count": 31.0,
      "yizi_count": 5.0,
      "shouban": 40.0,
      "er_lb": 3.0,
      "san_lb": 7.0,
      "si_lb": 1.0,
      "wu_lb": 0.0,
      "zt_925": 9.0,
      "t_before10": 30.0,
      "t_1000_1130": 14.0,
      "t_1300_1400": 4.0,
      "t_1400_1500": 3.0,
      "limit_broken_count": 19.0,
      "seal_rate": 75.95,
      "rate_1to2": 30.0,
      "rate_2to3": 33.33,
      "rate_3to4": 57.14,
      "lb_rate": 28.33,
      "lb_rate_prev": 33.33,
      "zt_amount": 1311.93,
      "total_amount": 3890.93,
      "sh_amount": 8979.55,
      "cyb_amount": 6134.82,
      "kcb_amount": 2214.21
    },
    {
      "date": "2026-02-13",
      "up_count": 1602.0,
      "down_count": 3829.0,
      "zt_all": 32.0,
      "dt_count": 16.0,
      "lb_count": 5.0,
      "up10_count": 38.0,
      "down9_count": 31.0,
      "yizi_count": 3.0,
      "shouban": 69.0,
      "er_lb": 100.0,
      "san_lb": 70.0,
      "si_lb": 100.0,
      "wu_lb": 0.0,
      "zt_925": 4.0,
      "t_before10": 77.0,
      "t_1000_1130": 74.0,
      "t_1300_1400": 67.0,
      "t_1400_1500": 75.0,
      "limit_broken_count": 12.0,
      "seal_rate": 72.73,
      "rate_1to2": 2.33,
      "rate_2to3": 25.0,
      "rate_3to4": 0.0,
      "lb_rate": 15.62,
      "lb_rate_prev": 8.33,
      "zt_amount": 796.82,
      "total_amount": 2060.82,
      "sh_amount": 8468.08,
      "cyb_amount": 5421.17,
      "kcb_amount": 2109.84
    },
    {
      "date": "2026-02-24",
      "up_count": 3905.0,
      "down_count": 1503.0,
      "zt_all": 91.0,
      "dt_count": 19.0,
      "lb_count": 7.0,
      "up10_count": 117.0,
      "down9_count": 48.0,
      "yizi_count": 3.0,
      "shouban": 43.0,
      "er_lb": 12.0,
      "san_lb": 1.0,
      "si_lb": 4.0,
      "wu_lb": 0.0,
      "zt_925": 9.0,
      "t_before10": 21.0,
      "t_1000_1130": 24.0,
      "t_1300_1400": 11.0,
      "t_1400_1500": 3.0,
      "limit_broken_count": 46.0,
      "seal_rate": 66.42,
      "rate_1to2": 14.81,
      "rate_2to3": 100.0,
      "rate_3to4": 66.67,
      "lb_rate": 7.69,
      "lb_rate_prev": 21.88,
      "zt_amount": 1775.64,
      "total_amount": 4310.64,
      "sh_amount": 9386.11,
      "cyb_amount": 5933.53,
      "kcb_amount": 2280.83
    },
    {
      "date": "2026-02-25",
      "up_count": 3722.0,
      "down_count": 1723.0,
      "zt_all": 74.0,
      "dt_count": 6.0,
      "lb_count": 17.0,
      "up10_count": 101.0,
      "down9_count": 15.0,
      "yizi_count": 2.0,
      "shouban": 66.0,
      "er_lb": 100.0,
      "san_lb": 100.0,
      "si_lb": 100.0,
      "wu_lb": 0.0,
      "zt_925": 3.0,
      "t_before10": 75.0,
      "t_1000_1130": 80.0,
      "t_1300_1400": 73.0,
      "t_1400_1500": 60.0,
      "limit_broken_count": 37.0,
      "seal_rate": 66.67,
      "rate_1to2": 15.48,
      "rate_2to3": 50.0,
      "rate_3to4": 100.0,
      "lb_rate": 22.97,
      "lb_rate_prev": 18.68,
      "zt_amount": 1912.4,
      "total_amount": 4610.4,
      "sh_amount": 10859.7,
      "cyb_amount": 6222.33,
      "kcb_amount": 2373.93
    },
    {
      "date": "2026-02-26",
      "up_count": 2577.0,
      "down_count": 2870.0,
      "zt_all": 63.0,
      "dt_count": 7.0,
      "lb_count": 9.0,
      "up10_count": 89.0,
      "down9_count": 14.0,
      "yizi_count": 2.0,
      "shouban": 27.0,
      "er_lb": 1.0,
      "san_lb": 3.0,
      "si_lb": 0.0,
      "wu_lb": 1.0,
      "zt_925": 3.0,
      "t_before10": 18.0,
      "t_1000_1130": 12.0,
      "t_1300_1400": 2.0,
      "t_1400_1500": 0.0,
      "limit_broken_count": 24.0,
      "seal_rate": 72.41,
      "rate_1to2": 8.77,
      "rate_2to3": 15.38,
      "rate_3to4": 50.0,
      "lb_rate": 14.29,
      "lb_rate_prev": 12.16,
      "zt_amount": 1599.86,
      "total_amount": 4280.86,
      "sh_amount": 10672.0,
      "cyb_amount": 6927.7,
      "kcb_amount": 2673.61
    },
    {
      "date": "2026-02-27",
      "up_count": 3370.0,
      "down_count": 2094.0,
      "zt_all": 75.0,
      "dt_count": 3.0,
      "lb_count": 11.0,
      "up10_count": 93.0,
      "down9_count": 8.0,
      "yizi_count": 2.0,
      "shouban": 69.0,
      "er_lb": 50.0,
      "san_lb": 75.0,
      "si_lb": 0.0,
      "wu_lb": 50.0,
      "zt_925": 3.0,
      "t_before10": 72.0,
      "t_1000_1130": 75.0,
      "t_1300_1400": 67.0,
      "t_1400_1500": 0.0,
      "limit_broken_count": 18.0,
      "seal_rate": 80.65,
      "rate_1to2": 11.11,
      "rate_2to3": 60.0,
      "rate_3to4": 50.0,
      "lb_rate": 14.67,
      "lb_rate_prev": 17.46,
      "zt_amount": 1818.13,
      "total_amount": 4150.13,
      "sh_amount": 10723.7,
      "cyb_amount": 6627.59,
      "kcb_amount": 2576.95
    },
    {
      "date": "2026-03-02",
      "up_count": 1231.0,
      "down_count": 4152.0,
      "zt_all": 91.0,
      "dt_count": 11.0,
      "lb_count": 20.0,
      "up10_count": 118.0,
      "down9_count": 27.0,
      "yizi_count": 8.0,
      "shouban": 84.0,
      "er_lb": 4.0,
      "san_lb": 1.0,
      "si_lb": 2.0,
      "wu_lb": 0.0,
      "zt_925": 24.0,
      "t_before10": 51.0,
      "t_1000_1130": 22.0,
      "t_1300_1400": 12.0,
      "t_1400_1500": 6.0,
      "limit_broken_count": 28.0,
      "seal_rate": 76.47,
      "rate_1to2": 26.56,
      "rate_2to3": 50.0,
      "rate_3to4": 0.0,
      "lb_rate": 21.98,
      "lb_rate_prev": 26.67,
      "zt_amount": 2721.31,
      "total_amount": 6063.31,
      "sh_amount": 13458.9,
      "cyb_amount": 7384.03,
      "kcb_amount": 2935.47
    },
    {
      "date": "2026-03-03",
      "up_count": 652.0,
      "down_count": 4714.0,
      "zt_all": 77.0,
      "dt_count": 60.0,
      "lb_count": 37.0,
      "up10_count": 83.0,
      "down9_count": 232.0,
      "yizi_count": 7.0,
      "shouban": 65.0,
      "er_lb": 57.0,
      "san_lb": 100.0,
      "si_lb": 100.0,
      "wu_lb": 0.0,
      "zt_925": 3.0,
      "t_before10": 75.0,
      "t_1000_1130": 67.0,
      "t_1300_1400": 57.0,
      "t_1400_1500": 46.0,
      "limit_broken_count": 30.0,
      "seal_rate": 71.96,
      "rate_1to2": 46.48,
      "rate_2to3": 23.53,
      "rate_3to4": 0.0,
      "lb_rate": 48.05,
      "lb_rate_prev": 40.66,
      "zt_amount": 1874.61,
      "total_amount": 4266.61,
      "sh_amount": 14148.4,
      "cyb_amount": 7435.7,
      "kcb_amount": 3039.86
    }
  ],
  "fetched_at": "2026-03-03 08:54:34"
}